ORELWEbyST/__init__.py
ORELWEbyST-0.5.dist-info/METADATA
ORELWEbyST-0.5.dist-info/WHEEL
ORELWEbyST-0.5.dist-info/top_level.txt
ORELWEbyST-0.5.dist-info/RECORD
