Metadata-Version: 2.1
Name: ORELWEbyST
Version: 0.5
Author: Jaehwan Park
Author-email: jpark127@utk.edu
Requires-Python: >=3.6
